improving_transformers_world_model/__init__.py
improving_transformers_world_model/agent.py
improving_transformers_world_model/distributed.py
improving_transformers_world_model/mock_env.py
improving_transformers_world_model/tensor_typing.py
improving_transformers_world_model/world_model.py
improving_transformers_world_model-0.0.59.dist-info/METADATA
improving_transformers_world_model-0.0.59.dist-info/WHEEL
improving_transformers_world_model-0.0.59.dist-info/licenses/LICENSE
improving_transformers_world_model-0.0.59.dist-info/RECORD
