Metadata-Version: 2.4
Name: improving-transformers-world-model
Version: 0.0.59
Summary: Improving Transformers World Model for RL
Project-URL: Homepage, https://pypi.org/project/improving-transformers-world-model-for-rl/
Project-URL: Repository, https://github.com/lucidrains/improving-transformers-world-model-for-rl
Author-email: Phil Wang <lucidrains@gmail.com>
License: MIT License
License-File: LICENSE
Keywords: artificial intelligence,attention mechanism,deep learning,transformer,world model
Classifier: Development Status :: 4 - Beta
Classifier: Intended Audience :: Developers
Classifier: License :: OSI Approved :: MIT License
Classifier: Programming Language :: Python :: 3.9
Classifier: Topic :: Scientific/Engineering :: Artificial Intelligence
Requires-Python: >=3.9
Requires-Dist: adam-atan2-pytorch>=0.1.18
Requires-Dist: assoc-scan>=0.0.2
Requires-Dist: einops>=0.8.0
Requires-Dist: einx>=0.3.0
Requires-Dist: ema-pytorch>=0.7.7
Requires-Dist: evolutionary-policy-optimization>=0.1.7
Requires-Dist: hl-gauss-pytorch>=0.1.21
Requires-Dist: hyper-connections>=0.1.11
Requires-Dist: jaxtyping
Requires-Dist: ninja
Requires-Dist: pufferlib>=2.0.6
Requires-Dist: rotary-embedding-torch>=0.8.6
Requires-Dist: torch>=2.2
Requires-Dist: tqdm
Requires-Dist: vector-quantize-pytorch>=1.22.3
Provides-Extra: examples
Provides-Extra: test
Requires-Dist: pytest; extra == 'test'
